MANIFEST.in
README.rst
setup.py
milksets/__init__.py
milksets/milksets_version.py
milksets/transformations.py
milksets/utils.py
milksets/vtypes.py
milksets.egg-info/PKG-INFO
milksets.egg-info/SOURCES.txt
milksets.egg-info/dependency_links.txt
milksets.egg-info/top_level.txt
milksets/abalone/__init__.py
milksets/abalone/abalone.py
milksets/abalone/data/abalone.data.gz
milksets/abalone/data/abalone.names
milksets/census/__init__.py
milksets/census/census.py
milksets/census/data/census-income.data.gz
milksets/census/data/census-income.names
milksets/census/data/census-income.test.gz
milksets/german/__init__.py
milksets/german/german.py
milksets/german/data/german.pp.gz
milksets/iris/__init__.py
milksets/iris/iris.py
milksets/iris/data/correct.data.bz2
milksets/iris/data/download.sh
milksets/iris/data/iris.names
milksets/iris/data/uci_mistake.data.bz2
milksets/murphy_hela_slf7dna/__init__.py
milksets/murphy_hela_slf7dna/murphy_hela2d_slf7dna.py
milksets/murphy_hela_slf7dna/data/compute.py
milksets/murphy_hela_slf7dna/data/murphylab.npz
milksets/page_blocks/__init__.py
milksets/page_blocks/page_blocks.py
milksets/page_blocks/data/page-blocks.data.gz
milksets/page_blocks/data/page-blocks.names
milksets/scene/__init__.py
milksets/scene/scene.py
milksets/scene/data/scene_test.bz2
milksets/scene/data/scene_train.bz2
milksets/seeds/__init__.py
milksets/seeds/seeds.py
milksets/seeds/data/download.sh
milksets/seeds/data/seeds_dataset.txt.gz
milksets/tests/__init__.py
milksets/tests/test_abalone.py
milksets/tests/test_census.py
milksets/tests/test_classification_loaders.py
milksets/tests/test_iris.py
milksets/tests/test_scene.py
milksets/tests/test_transformations.py
milksets/wine/__init__.py
milksets/wine/wine.py
milksets/wine/data/README.wine
milksets/wine/data/wine.data
milksets/wine/data/wine.names
milksets/yeast/__init__.py
milksets/yeast/yeast.py
milksets/yeast/data/yeast.data.gz
milksets/yeast/data/yeast.names