Metadata-Version: 1.0
Name: milksets
Version: 0.2
Summary: Milk sets: Machine Learning Datasets
Home-page: http://luispedro.org/software/milksets/
Author: Luis Pedro Coelho
Author-email: luis@luispedro.org
License: UNKNOWN
Platform: UNKNOWN
